LICENSE
setup.py
ilum_job_api/__init__.py
ilum_job_api.egg-info/PKG-INFO
ilum_job_api.egg-info/SOURCES.txt
ilum_job_api.egg-info/dependency_links.txt
ilum_job_api.egg-info/top_level.txt
ilum_job_api/api/__init__.py
ilum_job_api/api/job_interface.py