Metadata-Version: 2.1
Name: ilum-job-api
Version: 5.2.0rc1
Summary: Ilum job python api
Home-page: https://ilum.cloud
Author: ilum.cloud
Author-email: info@ilum.cloud
License: UNKNOWN
Platform: UNKNOWN
License-File: LICENSE
